<?xml version="1.0" encoding="UTF-8"?>
<beans xmlns="http://www.springframework.org/schema/beans"
	xmlns:xsi="http://www.w3.org/2001/XMLSchema-instance"
	xmlns:aop="http://www.springframework.org/schema/aop"
	xsi:schemaLocation="http://www.springframework.org/schema/beans http://www.springframework.org/schema/beans/spring-beans-4.3.xsd
		http://www.springframework.org/schema/aop http://www.springframework.org/schema/aop/spring-aop-4.3.xsd">
	
	<aop:aspectj-autoproxy/>
	<bean id="loggingAspectJ" class="com.learn.aspects.LoggingAspectJ"/>
	
	<bean id="e1" class="com.learn.models.Employee">
		<property name="age" value="41"/>
		<property name="firstName" value="learn"/>
		<property name="lastName" value="Joshi"/>
		<property name="salary" value="40000"/>
	</bean>
</beans>
